coo_imgSorter/RGBs.py
coo_imgSorter/Similarity.py
coo_imgSorter/__init__.py
coo_imgSorter/util/__init__.py
coo_imgSorter/util/file.py
coo_imgSorter/util/image.py
coo_img_sorter-0.0.1.dist-info/LICENSE
coo_img_sorter-0.0.1.dist-info/METADATA
coo_img_sorter-0.0.1.dist-info/WHEEL
coo_img_sorter-0.0.1.dist-info/top_level.txt
coo_img_sorter-0.0.1.dist-info/RECORD
