Metadata-Version: 2.1
Name: coo-img-sorter
Version: 0.0.1
Summary: 多种图片分类工具脚手架
Home-page: https://github.com/xcenweb/coo-img-sorter
Author: xcenweb
Author-email: xcenweb@qq.com
License: MIT
Platform: UNKNOWN
Requires-Python: >=3.8
Requires-Dist: numpy ~=1.25.2
Requires-Dist: Pillow ~=10.0.0
